flaim/__init__.py
flaim/layers/__init__.py
flaim/layers/acts.py
flaim/layers/bam.py
flaim/layers/cbam.py
flaim/layers/conv.py
flaim/layers/eca.py
flaim/layers/gn_conv.py
flaim/layers/grn.py
flaim/layers/head.py
flaim/layers/identity.py
flaim/layers/layer_scale.py
flaim/layers/lin_norm_act.py
flaim/layers/lka.py
flaim/layers/meta_former.py
flaim/layers/mhsa.py
flaim/layers/mlp.py
flaim/layers/pool.py
flaim/layers/rel_pos_embed.py
flaim/layers/se.py
flaim/layers/sk.py
flaim/layers/splat.py
flaim/layers/tuplify.py
flaim/layers/vit_layers.py
flaim/layers/window.py
flaim/layers/xca.py
flaim/models/__init__.py
flaim/models/cait.py
flaim/models/convmixer.py
flaim/models/convnext.py
flaim/models/efficientnetv2.py
flaim/models/factory.py
flaim/models/gcvit.py
flaim/models/hornet.py
flaim/models/maxvit.py
flaim/models/nest.py
flaim/models/pvtv2.py
flaim/models/regnet.py
flaim/models/resnet.py
flaim/models/swin.py
flaim/models/van.py
flaim/models/vgg.py
flaim/models/vit.py
flaim/models/xcit.py
flaim-0.0.5.dist-info/LICENSE.md
flaim-0.0.5.dist-info/METADATA
flaim-0.0.5.dist-info/WHEEL
flaim-0.0.5.dist-info/top_level.txt
flaim-0.0.5.dist-info/RECORD
