Metadata-Version: 2.1
Name: flaim
Version: 0.0.5
Summary: Flax Image Models
Home-page: https://github.com/bobmcdear/flaim
Author: Borna Ahmadzadeh
Author-email: borna.ahz@gmail.com
License: GNU
Keywords: computer vision,machine learning,deep learning,jax,flax
Requires-Python: >=3.8
License-File: LICENSE.md
Requires-Dist: jaxlib
Requires-Dist: numpy (>=1.20)
Requires-Dist: jax (>=0.3.23)
Requires-Dist: flax (>=0.6.0)
